yw/__init__.py
yw-0.0.9.dist-info/licenses/LICENSE
yw-0.0.9.dist-info/METADATA
yw-0.0.9.dist-info/WHEEL
yw-0.0.9.dist-info/top_level.txt
yw-0.0.9.dist-info/RECORD
