Metadata-Version: 2.4
Name: yw
Version: 0.0.9
Summary: Audio Layers
Home-page: https://github.com/t-c-w/yw
Author: Thor Whalen
License: apache-2.0
Platform: any
License-File: LICENSE
Dynamic: license-file
